labelme/__init__.py
labelme/__main__.py
labelme/_label_file.py
labelme/app.py
labelme/shape.py
labelme/testing.py
labelme/_automation/__init__.py
labelme/_automation/_osam_session.py
labelme/_automation/bbox_from_text.py
labelme/_automation/polygon_from_mask.py
labelme/cli/__init__.py
labelme/cli/draw_json.py
labelme/cli/draw_label_png.py
labelme/cli/export_json.py
labelme/cli/on_docker.py
labelme/config/__init__.py
labelme/config/default_config.yaml
labelme/icons/ai-mask.svg
labelme/icons/ai-polygon.svg
labelme/icons/arrow-fat-left.svg
labelme/icons/arrow-fat-right.svg
labelme/icons/arrow-u-up-left.svg
labelme/icons/brightness-contrast.svg
labelme/icons/circle.svg
labelme/icons/circles-four.svg
labelme/icons/copy.svg
labelme/icons/eye.svg
labelme/icons/file-x.svg
labelme/icons/floppy-disk.svg
labelme/icons/folder-open.svg
labelme/icons/folders.svg
labelme/icons/frame-arrows-horizontal.svg
labelme/icons/frame-corners.svg
labelme/icons/icon-128.png
labelme/icons/icon-16.png
labelme/icons/icon-256.png
labelme/icons/icon-32.png
labelme/icons/icon-48.png
labelme/icons/icon-64.png
labelme/icons/icon.ico
labelme/icons/image-square.svg
labelme/icons/info.svg
labelme/icons/line-segment.svg
labelme/icons/line-segments.svg
labelme/icons/magnifying-glass-minus.svg
labelme/icons/magnifying-glass-plus.svg
labelme/icons/note-pencil.svg
labelme/icons/paint-bucket.svg
labelme/icons/polygon.svg
labelme/icons/question.svg
labelme/icons/rectangle.svg
labelme/icons/trash.svg
labelme/icons/x-circle.svg
labelme/translate/de_DE.qm
labelme/translate/de_DE.ts
labelme/translate/es_ES.qm
labelme/translate/es_ES.ts
labelme/translate/fa_IR.qm
labelme/translate/fa_IR.ts
labelme/translate/fr_FR.qm
labelme/translate/fr_FR.ts
labelme/translate/hu_HU.qm
labelme/translate/hu_HU.ts
labelme/translate/it_IT.qm
labelme/translate/it_IT.ts
labelme/translate/ja_JP.qm
labelme/translate/ja_JP.ts
labelme/translate/ko_KR.qm
labelme/translate/ko_KR.ts
labelme/translate/nl_NL.qm
labelme/translate/nl_NL.ts
labelme-5.11.2.dist-info/METADATA
labelme-5.11.2.dist-info/WHEEL
labelme-5.11.2.dist-info/entry_points.txt
labelme-5.11.2.dist-info/licenses/LICENSE
labelme-5.11.2.dist-info/RECORD
